nnlogicalop/__init__.py
nnlogicalop/scripts/__init__.py
nnlogicalop/scripts/andGate.py
nnlogicalop/scripts/nandGate.py
nnlogicalop/scripts/norGate.py
nnlogicalop/scripts/notGate.py
nnlogicalop/scripts/orGate.py
nnlogicalop-0.0.0.dist-info/METADATA
nnlogicalop-0.0.0.dist-info/WHEEL
nnlogicalop-0.0.0.dist-info/top_level.txt
nnlogicalop-0.0.0.dist-info/RECORD
